sys_path.py
pkg1/__init__.py
pkg1/pkg1.py
chrm_test-1.0.2.dist-info/LICENSE
chrm_test-1.0.2.dist-info/METADATA
chrm_test-1.0.2.dist-info/WHEEL
chrm_test-1.0.2.dist-info/top_level.txt
chrm_test-1.0.2.dist-info/RECORD
