Metadata-Version: 2.1
Name: chrm-test
Version: 1.0.2
Summary: chrm test
Home-page: UNKNOWN
Author: chrm
Author-email: chrm@chrm.com
License: UNKNOWN
Platform: UNKNOWN
